libtad/__init__.py
libtad/astrodata_service.py
libtad/astronomy_service.py
libtad/authentication.py
libtad/base_service.py
libtad/business_date_service.py
libtad/business_duration_service.py
libtad/constants.py
libtad/convert_time_service.py
libtad/dst_service.py
libtad/holidays_service.py
libtad/places_service.py
libtad/time_service.py
libtad/common/__init__.py
libtad/common/exceptions.py
libtad/common/xml_utils.py
libtad/datatypes/__init__.py
libtad/datatypes/astro/__init__.py
libtad/datatypes/astro/astronomy.py
libtad/datatypes/astro/astronomy_current.py
libtad/datatypes/astro/astronomy_day.py
libtad/datatypes/astro/astronomy_day_event.py
libtad/datatypes/astro/astronomy_event.py
libtad/datatypes/astro/astronomy_event_class.py
libtad/datatypes/astro/astronomy_event_code.py
libtad/datatypes/astro/astronomy_event_type.py
libtad/datatypes/astro/astronomy_location.py
libtad/datatypes/astro/astronomy_object_details.py
libtad/datatypes/astro/astronomy_object_type.py
libtad/datatypes/astro/astronomy_special.py
libtad/datatypes/astro/astronomy_special_type.py
libtad/datatypes/astro/moon_phase.py
libtad/datatypes/business/__init__.py
libtad/datatypes/business/business_dates.py
libtad/datatypes/business/business_days_filter_type.py
libtad/datatypes/business/business_days_operator_type.py
libtad/datatypes/business/business_filter_method.py
libtad/datatypes/business/business_holiday_type.py
libtad/datatypes/business/period_type.py
libtad/datatypes/business/weekdays_type.py
libtad/datatypes/converted_times/__init__.py
libtad/datatypes/converted_times/converted_times.py
libtad/datatypes/dst/__init__.py
libtad/datatypes/dst/dst.py
libtad/datatypes/dst/dst_special_type.py
libtad/datatypes/holidays/__init__.py
libtad/datatypes/holidays/holiday.py
libtad/datatypes/holidays/holiday_state.py
libtad/datatypes/holidays/holiday_type.py
libtad/datatypes/places/__init__.py
libtad/datatypes/places/coordinates.py
libtad/datatypes/places/country.py
libtad/datatypes/places/geo.py
libtad-1.1.1.dist-info/LICENSE
libtad-1.1.1.dist-info/METADATA
libtad-1.1.1.dist-info/WHEEL
libtad-1.1.1.dist-info/top_level.txt
libtad-1.1.1.dist-info/RECORD
